LICENSE.txt
MANIFEST.in
README.rst
demo.ini
setup.cfg
setup.py
deform_jinja2/__init__.py
deform_jinja2/demo.py
deform_jinja2/forms.py
deform_jinja2/test.py
deform_jinja2/translator.py
deform_jinja2.egg-info/PKG-INFO
deform_jinja2.egg-info/SOURCES.txt
deform_jinja2.egg-info/dependency_links.txt
deform_jinja2.egg-info/not-zip-safe
deform_jinja2.egg-info/requires.txt
deform_jinja2.egg-info/top_level.txt
deform_jinja2/bootstrap_templates/autocomplete_input.jinja2
deform_jinja2/bootstrap_templates/checkbox.jinja2
deform_jinja2/bootstrap_templates/checkbox_choice.jinja2
deform_jinja2/bootstrap_templates/checked_input.jinja2
deform_jinja2/bootstrap_templates/checked_password.jinja2
deform_jinja2/bootstrap_templates/dateinput.jinja2
deform_jinja2/bootstrap_templates/dateparts.jinja2
deform_jinja2/bootstrap_templates/datetimeinput.jinja2
deform_jinja2/bootstrap_templates/file.txt
deform_jinja2/bootstrap_templates/file_upload.jinja2
deform_jinja2/bootstrap_templates/form.jinja2
deform_jinja2/bootstrap_templates/hidden.jinja2
deform_jinja2/bootstrap_templates/mapping.jinja2
deform_jinja2/bootstrap_templates/mapping_item.jinja2
deform_jinja2/bootstrap_templates/password.jinja2
deform_jinja2/bootstrap_templates/radio_choice.jinja2
deform_jinja2/bootstrap_templates/richtext.jinja2
deform_jinja2/bootstrap_templates/select.jinja2
deform_jinja2/bootstrap_templates/sequence.jinja2
deform_jinja2/bootstrap_templates/sequence_item.jinja2
deform_jinja2/bootstrap_templates/textarea.jinja2
deform_jinja2/bootstrap_templates/textinput.jinja2
deform_jinja2/bootstrap_templates/readonly/checkbox.jinja2
deform_jinja2/bootstrap_templates/readonly/checkbox_choice.jinja2
deform_jinja2/bootstrap_templates/readonly/checked_input.jinja2
deform_jinja2/bootstrap_templates/readonly/checked_password.jinja2
deform_jinja2/bootstrap_templates/readonly/dateparts.jinja2
deform_jinja2/bootstrap_templates/readonly/file_upload.jinja2
deform_jinja2/bootstrap_templates/readonly/form.jinja2
deform_jinja2/bootstrap_templates/readonly/mapping.jinja2
deform_jinja2/bootstrap_templates/readonly/mapping_item.jinja2
deform_jinja2/bootstrap_templates/readonly/password.jinja2
deform_jinja2/bootstrap_templates/readonly/radio_choice.jinja2
