Metadata-Version: 1.1
Name: deform-jinja2
Version: 0.5
Summary: Jinja2 templates for Deform widgets
Home-page: https://github.com/sontek/deform_jinja2
Author: John Anderson
Author-email: sontek@gmail.com
License: UNKNOWN
Keywords: web forms form generation schema validation
Platform: UNKNOWN
Classifier: Intended Audience :: Developers
Classifier: Programming Language :: Python
